libname/EyeBlinker.py
libname/__init__.py
eyeBlinkSensor-0.0.2.dist-info/METADATA
eyeBlinkSensor-0.0.2.dist-info/WHEEL
eyeBlinkSensor-0.0.2.dist-info/top_level.txt
eyeBlinkSensor-0.0.2.dist-info/RECORD
